gbnnetwork/BNetwork.py
gbnnetwork/__init__.py
gbnnetwork/test_network.py
gbnnetwork-1.3.0.dist-info/METADATA
gbnnetwork-1.3.0.dist-info/WHEEL
gbnnetwork-1.3.0.dist-info/top_level.txt
gbnnetwork-1.3.0.dist-info/RECORD
