Metadata-Version: 2.1
Name: gbnnetwork
Version: 1.3.0
Summary: Implementation of Bayesian network.
Author: Guillermo
Author-email: san191517@uvg.edu.gt
Keywords: python,probability,bayes
Classifier: Development Status :: 1 - Planning
Classifier: Intended Audience :: Developers
Classifier: Programming Language :: Python :: 3
Classifier: Operating System :: Unix
Classifier: Operating System :: MacOS :: MacOS X
Classifier: Operating System :: Microsoft :: Windows
